Workbook

Sheet Structure budgetaire
A1: Sauve un arbre - Structure budgetaire generale
A3: Code | B3: Libelle | C3: Niveau
A4: 1 | B4: Frais generaux | C4: 0
A5: 1.1 | B5: Salaires | C5: 1
A6: 1.1.1 | B6: Directeur | C6: 2
A7: 1.1.2 | B7: Responsable financier | C7: 2
A8: 1.1.3 | B8: Charge de programme | C8: 2
A9: 1.1.4 | B9: Responsable communication | C9: 2
A10: 1.1.5 | B10: Formateurs (x2) | C10: 2
A11: 1.2 | B11: Bureaux | C11: 1
A12: 1.2.1 | B12: Loyer | C12: 2
A13: 1.2.2 | B13: Charges (eau/electricite/internet) | C13: 2
A14: 1.3 | B14: Frais administratifs | C14: 1
A15: 1.3.1 | B15: Fournitures de bureau | C15: 2
... A34: 2.3.5 | B34: Coordination pedagogique | C34: 2

Sheet Budget previsionnel
A1: Budget previsionnel par projet et par bailleur
A3: Code ligne | B3: Libelle ligne budgetaire | C3: Projet | D3: Bailleur | E3: Montant (EUR) | F3: % ligne
A4: 2.1.1 | B4: Frais d'animation festival | C4: Projet A | D4: UE | E4: 8000 | F4: =E4/SUMIFS($E$4:$E$27,$C$4:$C$27,C4) -> 0.4
A5: 2.1.2 | B5: Materiel pedagogique | C5: Projet A | D5: UE | E5: 5000 | F5: =E5/SUMIFS($E$4:$E$27,$C$4:$C$27,C5) -> 0.25
A6: 2.1.3 | B6: Deplacements / missions | C6: Projet A | D6: UE | E6: 4000 | F6: =E6/SUMIFS($E$4:$E$27,$C$4:$C$27,C6) -> 0.2
A7: 2.1.4 | B7: Communication | C7: Projet A | D7: UE | E7: 3000 | F7: =E7/SUMIFS($E$4:$E$27,$C$4:$C$27,C7) -> 0.15
A8: 2.2.1 | B8: Formateurs terrain | C8: Projet B | D8: UE | E8: 9000 | F8: =E8/SUMIFS($E$4:$E$27,$C$4:$C$27,C8) -> 0.18
A9: 2.2.1 | B9: Formateurs terrain | C9: Projet B | D9: Fonds propres | E9: 9000 | F9: =E9/SUMIFS($E$4:$E$27,$C$4:$C$27,C9) -> 0.18
A10: 2.2.2 | B10: Deplacements / missions | C10: Projet B | D10: UE | E10: 6000 | F10: =E10/SUMIFS($E$4:$E$27,$C$4:$C$27,C10) -> 0.12
A11: 2.2.2 | B11: Deplacements / missions | C11: Projet B | D11: Fonds propres | E11: 6000 | F11: =E11/SUMIFS($E$4:$E$27,$C$4:$C$27,C11) -> 0.12
A12: 2.2.3 | B12: Materiel pedagogique | C12: Projet B | D12: UE | E12: 4000 | F12: =E12/SUMIFS($E$4:$E$27,$C$4:$C$27,C12) -> 0.08
A13: 2.2.3 | B13: Materiel pedagogique | C13: Projet B | D13: Fonds propres | E13: 4000 | F13: =E13/SUMIFS($E$4:$E$27,$C$4:$C$27,C13) -> 0.08
A14: 2.2.4 | B14: Location de salles | C14: Projet B | D14: UE | E14: 3500 | F14: =E14/SUMIFS($E$4:$E$27,$C$4:$C$27,C14) -> 0.07
A15: 2.2.4 | B15: Location de salles | C15: Projet B | D15: Fonds propres | E15: 3500 | F15: =E15/SUMIFS($E$4:$E$27,$C$4:$C$27,C15) -> 0.07
... A27: 2.3.5 | B27: Coordination pedagogique | C27: Projet C | D27: BAD | E27: 5000 | F27: =E27/SUMIFS($E$4:$E$27,$C$4:$C$27,C27) -> 0.041666667
B29: TOTAL PAR PROJET
C30: Projet A | E30: =SUMIFS($E$4:$E$27,$C$4:$C$27,C30) -> 20000
C31: Projet B | E31: =SUMIFS($E$4:$E$27,$C$4:$C$27,C31) -> 50000
C32: Projet C | E32: =SUMIFS($E$4:$E$27,$C$4:$C$27,C32) -> 120000
B34: TOTAL GENERAL | E34: =SUM(E30,E31,E32) -> 190000

Sheet Grand livre
A1: Grand livre des depenses - juillet 2024 a juillet 2026
A3: Date | B3: N piece | C3: Projet | D3: Code ligne | E3: Libelle ligne budgetaire | F3: Bailleur | G3: Montant (EUR) | H3: Commentaire
A4: 15/03/2024 | B4: PC0001 | C4: Projet A | D4: 2.1.1 | E4: Frais d'animation festival | F4: UE | G4: 8000 | H4: Realisation festival ecoles 2024 - solde 100%
A5: 20/04/2024 | B5: PC0002 | C5: Projet A | D5: 2.1.2 | E5: Materiel pedagogique | F5: UE | G5: 5000 | H5: Realisation festival ecoles 2024 - solde 100%
A6: 10/06/2024 | B6: PC0003 | C6: Projet A | D6: 2.1.3 | E6: Deplacements / missions | F6: UE | G6: 4000 | H6: Realisation festival ecoles 2024 - solde 100%
A7: 05/09/2024 | B7: PC0004 | C7: Projet A | D7: 2.1.4 | E7: Communication | F7: UE | G7: 3000 | H7: Realisation festival ecoles 2024 - solde 100%
A8: 31/12/2024 | B8: PC0035 | C8: Frais generaux | D8: 1.1 | E8: Salaires | F8: Fonds propres | G8: 56800 | H8: Annee complete 2024
A9: 31/12/2024 | B9: PC0038 | C9: Frais generaux | D9: 1.2 | E9: Bureaux | F9: Fonds propres | G9: 6000 | H9: Annee complete 2024
A10: 31/12/2024 | B10: PC0041 | C10: Frais generaux | D10: 1.3 | E10: Frais administratifs | F10: Fonds propres | G10: 2800 | H10: Annee complete 2024
A11: 30/06/2025 | B11: PC0005 | C11: Projet B | D11: 2.2.1 | E11: Formateurs terrain | F11: UE | G11: 4050 | H11: Realisation 2025 - 90% alloc. annuelle (part UE)
A12: 30/06/2025 | B12: PC0006 | C12: Projet B | D12: 2.2.1 | E12: Formateurs terrain | F12: Fonds propres | G12: 4050 | H12: Realisation 2025 - 90% alloc. annuelle (part fonds propres)
A13: 30/06/2025 | B13: PC0009 | C13: Projet B | D13: 2.2.2 | E13: Deplacements / missions | F13: UE | G13: 2700 | H13: Realisation 2025 - 90% alloc. annuelle (part UE)
A14: 30/06/2025 | B14: PC0010 | C14: Projet B | D14: 2.2.2 | E14: Deplacements / missions | F14: Fonds propres | G14: 2700 | H14: Realisation 2025 - 90% alloc. annuelle (part fonds propres)
A15: 30/06/2025 | B15: PC0013 | C15: Projet B | D15: 2.2.3 | E15: Materiel pedagogique | F15: UE | G15: 1800 | H15: Realisation 2025 - 90% alloc. annuelle (part UE)
... A46: 30/06/2026 | B46: PC0043 | C46: Frais generaux | D46: 1.3 | E46: Frais administratifs | F46: Fonds propres | G46: 1540 | H46: Janvier a juin 2026 (partiel)
F48: TOTAL GENERAL DEPENSES | G48: =SUM(G4:G46) -> 291780

Sheet Synthese
A1: Synthese budget vs realise par projet et par bailleur (situation juillet 2026)
A3: Projet | B3: Bailleur | C3: Budget previsionnel (EUR) | D3: Depense a ce jour (EUR) | E3: % execution | F3: Reste a engager (EUR)
A4: Projet A | B4: UE | C4: =SUMIFS('Budget previsionnel'!$E$4:$E$27,'Budget previsionnel'!$C$4:$C$27,A4,'Budget previsionnel'!$D$4:$D$27,B4) -> 20000 | D4: =SUMIFS('Grand livre'!$G$4:$G$46,'Grand livre'!$C$4:$C$46,A4,'Grand livre'!$F$4:$F$46,B4) -> 20000 | E4: =IFERROR(D4/C4,0) -> 1 | F4: =C4-D4 -> 0
A5: Projet B | B5: UE | C5: =SUMIFS('Budget previsionnel'!$E$4:$E$27,'Budget previsionnel'!$C$4:$C$27,A5,'Budget previsionnel'!$D$4:$D$27,B5) -> 25000 | D5: =SUMIFS('Grand livre'!$G$4:$G$46,'Grand livre'!$C$4:$C$46,A5,'Grand livre'!$F$4:$F$46,B5) -> 16250 | E5: =IFERROR(D5/C5,0) -> 0.65 | F5: =C5-D5 -> 8750
A6: Projet B | B6: Fonds propres | C6: =SUMIFS('Budget previsionnel'!$E$4:$E$27,'Budget previsionnel'!$C$4:$C$27,A6,'Budget previsionnel'!$D$4:$D$27,B6) -> 25000 | D6: =SUMIFS('Grand livre'!$G$4:$G$46,'Grand livre'!$C$4:$C$46,A6,'Grand livre'!$F$4:$F$46,B6) -> 16250 | E6: =IFERROR(D6/C6,0) -> 0.65 | F6: =C6-D6 -> 8750
A7: Projet C | B7: UE | C7: =SUMIFS('Budget previsionnel'!$E$4:$E$27,'Budget previsionnel'!$C$4:$C$27,A7,'Budget previsionnel'!$D$4:$D$27,B7) -> 60000 | D7: =SUMIFS('Grand livre'!$G$4:$G$46,'Grand livre'!$C$4:$C$46,A7,'Grand livre'!$F$4:$F$46,B7) -> 36000 | E7: =IFERROR(D7/C7,0) -> 0.6 | F7: =C7-D7 -> 24000
A8: Projet C | B8: BAD | C8: =SUMIFS('Budget previsionnel'!$E$4:$E$27,'Budget previsionnel'!$C$4:$C$27,A8,'Budget previsionnel'!$D$4:$D$27,B8) -> 60000 | D8: =SUMIFS('Grand livre'!$G$4:$G$46,'Grand livre'!$C$4:$C$46,A8,'Grand livre'!$F$4:$F$46,B8) -> 36000 | E8: =IFERROR(D8/C8,0) -> 0.6 | F8: =C8-D8 -> 24000
B10: TOTAL GENERAL | C10: =SUM(C4:C8) -> 190000 | D10: =SUM(D4:D8) -> 124500 | E10: =IFERROR(D10/C10,0) -> 0.65526316 | F10: =SUM(F4:F8) -> 65500
A12: Hypotheses : depenses simulees a des fins pedagogiques (donnees fictives). Projet A cloture a 100% en 2024. Projet B execute a 90% de l'allocation 2025 et 40% de l'allocation 2026 (partielle, arretee a juillet 2026). Projet C execute a 60% du budget total en 2026 (partielle, arretee a juillet 2026).
